kvk_api_client.py
kvk/src/__init__.py
kvk/src/kvk_api_async_client.py
kvk/src/kvk_api_client.py
kvk/src/paths.py
kvk_api_client/__init__.py
kvk_api_client/async_client.py
kvk_api_client/paths.py
kvk_api_client/sync_client.py
tests/__init__.py
tests/test_async_kvk_api.py
tests/test_kvk_api.py
kvk_api_client-0.0.10.dist-info/LICENCE
kvk_api_client-0.0.10.dist-info/METADATA
kvk_api_client-0.0.10.dist-info/WHEEL
kvk_api_client-0.0.10.dist-info/top_level.txt
kvk_api_client-0.0.10.dist-info/RECORD
