Metadata-Version: 2.1
Name: kvk-api-client
Version: 0.0.10
Summary: Simple python wrapper for KVK api
Home-page: UNKNOWN
Author: Ugurcan Akpulat
License: UNKNOWN
Platform: UNKNOWN
Classifier: Programming Language :: Python :: 3
Classifier: License :: OSI Approved :: MIT License
Classifier: Operating System :: OS Independent
Requires-Python: >=3.6
Requires-Dist: python-dotenv (>=0.21.1)
Requires-Dist: requests (>=2.28.2)
Requires-Dist: aiohttp (>=3.8.5)
Provides-Extra: dev
Requires-Dist: pytest (==7.2.1) ; extra == 'dev'
Requires-Dist: pytest-asyncio (==0.21.1) ; extra == 'dev'
